[
    {
        "namezh": "乐在其中",
        "nameen": "13812345678"
    },
    {
        "namezh": "肖三",
        "nameen": "13923456789"
    },
    {
        "namezh": "新阳",
        "nameen": "13734567890"
    },
    {
        "namezh": "小Q",
        "nameen": "13645678901"
    },
    {
        "namezh": "王一一",
        "nameen": "13556789012"
    },
    {
        "namezh": "团子",
        "nameen": "13467890123"
    },
    {
        "namezh": "公少",
        "nameen": "13378901234"
    },
    {
        "namezh": "要上岸",
        "nameen": "13289012345"
    },
    {
        "namezh": "胡图图",
        "nameen": "13190123456"
    },
    {
        "namezh": "子涵",
        "nameen": "13001234567"
    },
    {
        "namezh": "梦如之",
        "nameen": "13503886827",
        "intention": "国企社工"
    },
    {
        "namezh": "浙大学",
        "nameen": "13503886827",
        "intention": "事业单位"
    },
    {
        "namezh": "阿松大",
        "nameen": "13503886827",
        "intention": "事业单位"
    }
]